awesome_well_mcp/WellStructure.exe
awesome_well_mcp/__init__.py
awesome_well_mcp/main.py
awesome_well_mcp-2.3.1.dist-info/METADATA
awesome_well_mcp-2.3.1.dist-info/WHEEL
awesome_well_mcp-2.3.1.dist-info/entry_points.txt
awesome_well_mcp-2.3.1.dist-info/licenses/LICENSE
awesome_well_mcp-2.3.1.dist-info/RECORD
