Metadata-Version: 2.4
Name: awesome_well_mcp
Version: 2.3.1
Summary: 井身结构图生成器 MCP 服务 - 基于井数据自动生成井身结构图
Project-URL: Homepage, https://github.com/elf004-star/elf004GH_vault_awesome_well_structure
Project-URL: Repository, https://github.com/elf004-star/elf004GH_vault_awesome_well_structure
Project-URL: Documentation, https://github.com/elf004-star/elf004GH_vault_awesome_well_structure#readme
Project-URL: Issues, https://github.com/elf004-star/elf004GH_vault_awesome_well_structure/issues
Author-email: awesome_well_mcp team <1873475824@qq.com>
License-File: LICENSE
Keywords: drilling,generator,mcp,petroleum,structure,well
Classifier: Development Status :: 4 - Beta
Classifier: Intended Audience :: Developers
Classifier: License :: OSI Approved :: MIT License
Classifier: Programming Language :: Python :: 3
Classifier: Programming Language :: Python :: 3.10
Classifier: Programming Language :: Python :: 3.11
Classifier: Programming Language :: Python :: 3.12
Classifier: Topic :: Scientific/Engineering
Classifier: Topic :: Software Development :: Libraries :: Python Modules
Requires-Python: >=3.10
Requires-Dist: mcp[cli]>=1.16.0
